{
  "version": "1",
  "accountAssociation": {
    "header": "eyJmaWQiOjEzMzE3NjIsInR5cGUiOiJhdXRoIiwia2V5IjoiMHgzRUQ0ZDhjYjU5NzUwYjE3YTExZTk3MTdGMEQ3NThBNTUzNDI2NmVEIn0",
    "payload": "eyJkb21haW4iOiJjb3B3cmFwcGVyLnh5eiJ9",
    "signature": "BVXbSBbAM1y69ztGluclQt5pYx7rlDSHnRbrZ5VXmYNc1AwUdEOYpso4nOshtB+QfCw1eiLZ43tzhFq7R/991xw="
  },
  "app": {
    "name": "cCOP Wrapper",
    "description": "Cross-chain bridge for cCOP tokens - Wrap and unwrap cCOP between Celo, Base, Arbitrum, Optimism, and Avalanche using Hyperlane's secure infrastructure.",
    "homeUrl": "https://copwrapper.xyz",
    "iconUrl": "https://copwrapper.xyz/icon.png",
    "splashImageUrl": "https://copwrapper.xyz/splash.png",
    "buttonTitle": "🌉 Bridge",
    "webhookUrl": "https://copwrapper.xyz/api/webhook",
    "categories": ["finance", "defi", "bridge"],
    "requiredCapabilities": ["wallet.getEthereumProvider", "actions.signIn"]
  },
  "frame": {
    "name": "cCOP Wrapper",
    "version": "1",
    "iconUrl": "https://copwrapper.xyz/icon.png",
    "homeUrl": "https://copwrapper.xyz",
    "imageUrl": "https://copwrapper.xyz/image.png",
    "splashImageUrl": "https://copwrapper.xyz/splash.png",
    "splashBackgroundColor": "#1a1a1a",
    "webhookUrl": "https://copwrapper.xyz/api/webhook",
    "description": "Secure cross-chain bridge for cCOP tokens. Lock cCOP on Celo and mint wcCOP on Base, Arbitrum, Optimism, or Avalanche.",
    "subtitle": "Cross-Chain cCOP Bridge",
    "primaryCategory": "finance"
  }
}

